dump_parser.py
wiki_dump_parser-1.0.0.dist-info/LICENSE
wiki_dump_parser-1.0.0.dist-info/METADATA
wiki_dump_parser-1.0.0.dist-info/WHEEL
wiki_dump_parser-1.0.0.dist-info/top_level.txt
wiki_dump_parser-1.0.0.dist-info/RECORD
