Metadata-Version: 2.1
Name: wiki-dump-parser
Version: 1.0.0
Summary: A simple but fast python script that reads a XML dump of a wiki and output the processed data in a CSV file.
Home-page: https://github.com/Grasia/wiki-scripts/tree/master/dump_parser
Author: Abel 'Akronix' Serrano Juste
Author-email: akronix5@gmail.com
License: AGPL-3.0
Keywords: wiki dump parser Wikia xml csv pandas proccessing history data
Platform: UNKNOWN
Requires-Python: >=3
